[{"id":"103369","id_users":"49","rif":"C-J312069503","nombre_cliente":"PARTES REPUESTOS FILTROS, C.A","num_fact":"18912","num_control":"34274","fecha_contab":"2026-07-13","fecha_venc":"2026-07-13","valor_moneda":721.3455999999999903593561612069606781005859375,"moneda":"USD","iva":247.132800000000003137756721116602420806884765625,"porcentaje_iva":16,"porcentaje_descuento":0,"descuento":0,"sub_total":1544.579999999999927240423858165740966796875,"total_fact":1791.712800000000015643308870494365692138671875,"visto":"Y","nota_credito":null,"DocumentLines":[{"id_detalle":"68500","id_producto":"675","codigo":"WP-8050","descripcion":"FILTRO COMBUSTIBLE MACK SECUNDARIO 483GB 471M","na_pedido":"3088","cantidad":12,"precio":13.28999999999999914734871708787977695465087890625,"total":159.479999999999989768184605054557323455810546875},{"id_detalle":"68501","id_producto":"326","codigo":"WCH-155","descripcion":"FILTRO ACEITE CATERPILLAR (CAT-1M-9156)","na_pedido":"3136","cantidad":12,"precio":6,"total":72},{"id_detalle":"68502","id_producto":"648","codigo":"WP-3401","descripcion":"FILTRO COMBUSTIBLE CARRIER-TRANSSICOLD. CON DRENADOR M8 X 1,5H","na_pedido":"3314","cantidad":12,"precio":7.5999999999999996447286321199499070644378662109375,"total":91.2000000000000028421709430404007434844970703125},{"id_detalle":"68503","id_producto":"538","codigo":"W-2801","descripcion":"FILTRO ACEITE FOTON AUMAN ETX 1834 BJ4183-290 WEICHAI, IH528250-RI","na_pedido":"3363","cantidad":24,"precio":8.800000000000000710542735760100185871124267578125,"total":211.19999999999998863131622783839702606201171875},{"id_detalle":"68504","id_producto":"402","codigo":"WC-3646","descripcion":"FILTRO ACEITE JOHN DEERE AT-39266","na_pedido":"3496","cantidad":6,"precio":7,"total":42},{"id_detalle":"68505","id_producto":"1218","codigo":"WPS-19821","descripcion":"FILTRO COMB\/SEPARADOR IVECO STRALIS, EUROCARGO 06-","na_pedido":"3496","cantidad":12,"precio":11,"total":132},{"id_detalle":"68506","id_producto":"661","codigo":"WP-4637","descripcion":"FILTRO ACEITE HIDR\u00c1ULICO FORD F-8000, TRACTOR 6600","na_pedido":"3505","cantidad":12,"precio":8.199999999999999289457264239899814128875732421875,"total":98.400000000000005684341886080801486968994140625},{"id_detalle":"68507","id_producto":"326","codigo":"WCH-155","descripcion":"FILTRO ACEITE CATERPILLAR (CAT-1M-9156)","na_pedido":"3546","cantidad":12,"precio":6,"total":72},{"id_detalle":"68508","id_producto":"1184","codigo":"WC-634","descripcion":"FILTRO COMBUSTIBLE PRIMARIO SINOTRUK BOLDEN S6, S7, S9","na_pedido":"3546","cantidad":12,"precio":11,"total":132},{"id_detalle":"68509","id_producto":"953","codigo":"WPS-10812","descripcion":"FILTRO COMB\/SEPARADOR FOTON AUMARK 2.5T, 3.0TON DRENADOR M8X1,25","na_pedido":"3566","cantidad":12,"precio":11.03999999999999914734871708787977695465087890625,"total":132.479999999999989768184605054557323455810546875},{"id_detalle":"68510","id_producto":"1187","codigo":"WCH-1501","descripcion":"FILTRO ACEITE ELEMENTO ISUZU NPR 19-","na_pedido":"3566","cantidad":12,"precio":6.5,"total":78},{"id_detalle":"68511","id_producto":"677","codigo":"WP-9407","descripcion":"FILTRO ACEITE VOLVO-JOHN DEERE- 51660 ACEITE BY PASS","na_pedido":"3566","cantidad":12,"precio":11.699999999999999289457264239899814128875732421875,"total":140.400000000000005684341886080801486968994140625},{"id_detalle":"68512","id_producto":"561","codigo":"W-36","descripcion":"FILTRO ACEITE CATEPILLAR.MASSEY FERGUNSON. FORD","na_pedido":"3566","cantidad":12,"precio":7.5999999999999996447286321199499070644378662109375,"total":91.2000000000000028421709430404007434844970703125},{"id_detalle":"68513","id_producto":"1201","codigo":"WPS-8687","descripcion":"FILTRO COMBUSTIBLE JAC HFC-4253","na_pedido":"3594","cantidad":6,"precio":15.3699999999999992184029906638897955417633056640625,"total":92.219999999999998863131622783839702606201171875}]},{"id":"99508","id_users":"49","rif":"C-J312069503","nombre_cliente":"PARTES REPUESTOS FILTROS, C.A","num_fact":"18911","num_control":"34273","fecha_contab":"2026-07-10","fecha_venc":"2026-07-10","valor_moneda":709.6934999999999718056642450392246246337890625,"moneda":"USD","iva":314.82400000000001227817847393453121185302734375,"porcentaje_iva":16,"porcentaje_descuento":0,"descuento":0,"sub_total":1967.65000000000009094947017729282379150390625,"total_fact":2282.474000000000160071067512035369873046875,"visto":"Y","nota_credito":null,"DocumentLines":[{"id_detalle":"67703","id_producto":"476","codigo":"WA-7127","descripcion":"FILTRO AIRE VOLKSWAGEN GOL 4L 1,8 (01-09)  PO=377127620 WIX 47035","na_pedido":"2951","cantidad":6,"precio":4.1500000000000003552713678800500929355621337890625,"total":24.89999999999999857891452847979962825775146484375},{"id_detalle":"67704","id_producto":"452","codigo":"WA-3901","descripcion":"FILTRO AIRE CHRYSLER JEEP CHEROKEE- RAM 2500 (94\/2004) WIX 46077","na_pedido":"2951","cantidad":6,"precio":5.5,"total":33},{"id_detalle":"67705","id_producto":"2164","codigo":"WCA-2342","descripcion":"FILTRO AIRE DONGFENG KINGRUN 210 (DFL1140B), FAW CA1053","na_pedido":"3062","cantidad":1,"precio":30,"total":30},{"id_detalle":"67706","id_producto":"2165","codigo":"WCA-2342 SY","descripcion":"FILTRO AIRE DONGFENG KENGRUN 210 (DFL1140B), FAW CA1053","na_pedido":"3062","cantidad":6,"precio":14,"total":84},{"id_detalle":"67707","id_producto":"201","codigo":"WCA-6512","descripcion":"FILTRO AIRE CAMION MACK SERIE CL 653 57MD42M","na_pedido":"3084","cantidad":4,"precio":60.35000000000000142108547152020037174224853515625,"total":241.400000000000005684341886080801486968994140625},{"id_detalle":"67708","id_producto":"212","codigo":"WCA-7244","descripcion":"FILTRO AIRE, ATLAS COPCO, DEUTZ 46430","na_pedido":"3136","cantidad":6,"precio":19.64999999999999857891452847979962825775146484375,"total":117.900000000000005684341886080801486968994140625},{"id_detalle":"67709","id_producto":"773","codigo":"WCA-7111","descripcion":"FILTRO AIRE NEW HOLLAND 7630 - IVECO- JOHN DEERE","na_pedido":"3155","cantidad":3,"precio":17.800000000000000710542735760100185871124267578125,"total":53.39999999999999857891452847979962825775146484375},{"id_detalle":"67710","id_producto":"201","codigo":"WCA-6512","descripcion":"FILTRO AIRE CAMION MACK SERIE CL 653 57MD42M","na_pedido":"3169","cantidad":2,"precio":60.35000000000000142108547152020037174224853515625,"total":120.7000000000000028421709430404007434844970703125},{"id_detalle":"67711","id_producto":"98","codigo":"WCA-224","descripcion":"FILTRO AIRE CATERPILLAR 215, 930T CAT-4M8047","na_pedido":"3248","cantidad":6,"precio":29.60000000000000142108547152020037174224853515625,"total":177.599999999999994315658113919198513031005859375},{"id_detalle":"67712","id_producto":"78","codigo":"WCA-1544","descripcion":"FILTRO AIRE ALLIS CHALMERS - MASSEY FERGUNSON","na_pedido":"3248","cantidad":6,"precio":15.1500000000000003552713678800500929355621337890625,"total":90.900000000000005684341886080801486968994140625},{"id_detalle":"67713","id_producto":"166","codigo":"WCA-5070","descripcion":"FILTRO AIRE CAMION NPR MOTOR ISUZU 4BDI SIN TURBO, JAC HFC 1035","na_pedido":"3314","cantidad":2,"precio":17.449999999999999289457264239899814128875732421875,"total":34.89999999999999857891452847979962825775146484375},{"id_detalle":"67714","id_producto":"127","codigo":"WCA-2590","descripcion":"FILTRO AIRE TRACTOR CATERPILLAR","na_pedido":"3392","cantidad":1,"precio":23.14999999999999857891452847979962825775146484375,"total":23.14999999999999857891452847979962825775146484375},{"id_detalle":"67715","id_producto":"100","codigo":"WCA-226","descripcion":"FILTRO AIRE JOHN DEERE 54336, CAT D5, D6, D7, 3208, 140G OEM 4M-9334, 7W-5317","na_pedido":"3446","cantidad":2,"precio":35.9500000000000028421709430404007434844970703125,"total":71.900000000000005684341886080801486968994140625},{"id_detalle":"67716","id_producto":"489","codigo":"WA-7775","descripcion":"FILTRO AIRE HYUNDAI ACCENT 1.5 28113-22051-0 WIX 46104","na_pedido":"3461","cantidad":12,"precio":4.0999999999999996447286321199499070644378662109375,"total":49.2000000000000028421709430404007434844970703125},{"id_detalle":"67717","id_producto":"105","codigo":"WCA-234","descripcion":"FILTRO AIRE CATERPILLAR CAT 2S-1287, 7M9046","na_pedido":"3462","cantidad":2,"precio":38,"total":76},{"id_detalle":"67718","id_producto":"1208","codigo":"WRA-10029","descripcion":"FILTRO AIRE MASSEY FERGUSSON 5650","na_pedido":"3496","cantidad":2,"precio":23.85000000000000142108547152020037174224853515625,"total":47.7000000000000028421709430404007434844970703125},{"id_detalle":"67719","id_producto":"2213","codigo":"WRA-10029 SY","descripcion":"FILTRO AIRE SECUNDARIO MASSEY FERGUSON 5650 16138004, 29149310, BOMAG5821149,","na_pedido":"3496","cantidad":2,"precio":9.1500000000000003552713678800500929355621337890625,"total":18.300000000000000710542735760100185871124267578125},{"id_detalle":"67720","id_producto":"72","codigo":"WCA-1533","descripcion":"FILTRO AIRE JOHN DEERE JD-AR-54336","na_pedido":"3496","cantidad":3,"precio":22.10000000000000142108547152020037174224853515625,"total":66.2999999999999971578290569595992565155029296875},{"id_detalle":"67721","id_producto":"191","codigo":"WCA-595","descripcion":"FILTRO AIRE FORD, KENWORTH, MACK 57MD33","na_pedido":"3505","cantidad":4,"precio":55.75,"total":223},{"id_detalle":"67722","id_producto":"202","codigo":"WCA-6645","descripcion":"FILTRO AIRE CAMION F-7000 MOTOR BRASILERO","na_pedido":"3505","cantidad":2,"precio":23.949999999999999289457264239899814128875732421875,"total":47.89999999999999857891452847979962825775146484375},{"id_detalle":"67723","id_producto":"479","codigo":"WA-7421","descripcion":"FILTRO AIRE BLAZER GENERAL MOTORS -CAMARO V6 (93\/95) WIX  46117","na_pedido":"3566","cantidad":12,"precio":5.45000000000000017763568394002504646778106689453125,"total":65.400000000000005684341886080801486968994140625},{"id_detalle":"67724","id_producto":"87","codigo":"WCA-1574","descripcion":"FILTRO AIRE FORD LN, LNT-8000, CAMION GURI","na_pedido":"3566","cantidad":2,"precio":36,"total":72},{"id_detalle":"67725","id_producto":"116","codigo":"WCA-253 SY","descripcion":"FILTRO AIRE SECUNDARIO FORD LN, LNT-8000 GURY","na_pedido":"3575","cantidad":6,"precio":6.9000000000000003552713678800500929355621337890625,"total":41.39999999999999857891452847979962825775146484375},{"id_detalle":"67726","id_producto":"584","codigo":"W-47","descripcion":"FILTRO ACEITE CASE JHON DEERE (AR-43634)","na_pedido":"3584","cantidad":8,"precio":13.800000000000000710542735760100185871124267578125,"total":110.400000000000005684341886080801486968994140625},{"id_detalle":"67727","id_producto":"127","codigo":"WCA-2590","descripcion":"FILTRO AIRE TRACTOR CATERPILLAR","na_pedido":"3584","cantidad":2,"precio":23.14999999999999857891452847979962825775146484375,"total":46.2999999999999971578290569595992565155029296875}]},{"id":"99482","id_users":"49","rif":"C-J312069503","nombre_cliente":"PARTES REPUESTOS FILTROS, C.A","num_fact":"18910","num_control":"34272","fecha_contab":"2026-07-10","fecha_venc":"2026-07-10","valor_moneda":709.6934999999999718056642450392246246337890625,"moneda":"USD","iva":161.9488000000000056388671509921550750732421875,"porcentaje_iva":16,"porcentaje_descuento":0,"descuento":0,"sub_total":1012.1799999999999499777914024889469146728515625,"total_fact":1174.12879999999995561665855348110198974609375,"visto":"Y","nota_credito":null,"DocumentLines":[{"id_detalle":"67683","id_producto":"750","codigo":"WRA-8193","descripcion":"FILTRO AIRE FREIGHTLINER MOTOR CATERPILLAR 3126 ( 95-04)","na_pedido":"3062","cantidad":1,"precio":34.0499999999999971578290569595992565155029296875,"total":34.0499999999999971578290569595992565155029296875},{"id_detalle":"67684","id_producto":"54","codigo":"WRA-8038","descripcion":"FILTRO AIRE CHEVROLET CHEYENNE, SILVERADO 97-99, GRAND BLAZER, GENERADOR WEICHAI WP4.1D120E201, WP4.1D66E200, WP4.1D100E200","na_pedido":"3097","cantidad":1,"precio":9.949999999999999289457264239899814128875732421875,"total":9.949999999999999289457264239899814128875732421875},{"id_detalle":"67685","id_producto":"989","codigo":"WRA-8193 SY","descripcion":"FILTRO AIRE SECUNDARIO FREIGHTLINER MOTOR CATERPILLAR 3126 (95-04)","na_pedido":"3140","cantidad":3,"precio":12.4000000000000003552713678800500929355621337890625,"total":37.2000000000000028421709430404007434844970703125},{"id_detalle":"67686","id_producto":"285","codigo":"WRA-9246","descripcion":"FILTRO AIRE THERMO KING ENCAVA 01-, MONTACARGAS CLARK, TOYOTA SERIE 6","na_pedido":"3155","cantidad":2,"precio":11,"total":22},{"id_detalle":"67687","id_producto":"285","codigo":"WRA-9246","descripcion":"FILTRO AIRE THERMO KING ENCAVA 01-, MONTACARGAS CLARK, TOYOTA SERIE 6","na_pedido":"3383","cantidad":12,"precio":11,"total":132},{"id_detalle":"67688","id_producto":"785","codigo":"WRA-9352 SY","descripcion":"FILTRO AIRE ATLAS COPCO\/MASSEY FERGUSON\/KOMATSU","na_pedido":"3446","cantidad":2,"precio":6.9000000000000003552713678800500929355621337890625,"total":13.800000000000000710542735760100185871124267578125},{"id_detalle":"67689","id_producto":"287","codigo":"WRA-9269","descripcion":"FILTRO AIRE CHEVROLET EXPRESS CARGO VAN","na_pedido":"3461","cantidad":6,"precio":16.89999999999999857891452847979962825775146484375,"total":101.400000000000005684341886080801486968994140625},{"id_detalle":"67690","id_producto":"268","codigo":"WRA-8204","descripcion":"FILTRO AIRE MERCEDES BENZ-PRIM (376 094 82 04)","na_pedido":"3496","cantidad":3,"precio":42.4500000000000028421709430404007434844970703125,"total":127.349999999999994315658113919198513031005859375},{"id_detalle":"67691","id_producto":"274","codigo":"WRA-8536 SY","descripcion":"FILTRO AIRE CATERPILLAR SECUNDARIO  123-6856","na_pedido":"3546","cantidad":6,"precio":17.949999999999999289457264239899814128875732421875,"total":107.7000000000000028421709430404007434844970703125},{"id_detalle":"67692","id_producto":"273","codigo":"WRA-8535","descripcion":"FILTRO AIRE PRIMARIO CATERPILLAR 123-6855","na_pedido":"3546","cantidad":1,"precio":50,"total":50},{"id_detalle":"67693","id_producto":"260","codigo":"WRA-7484","descripcion":"FILTRO AIRE CATERPILLAR 6I-2503","na_pedido":"3584","cantidad":2,"precio":43.39999999999999857891452847979962825775146484375,"total":86.7999999999999971578290569595992565155029296875},{"id_detalle":"67694","id_producto":"261","codigo":"WRA-7484 SY","descripcion":"FILTRO AIRE CATERPILLAR 6I-2504","na_pedido":"3584","cantidad":2,"precio":16.550000000000000710542735760100185871124267578125,"total":33.10000000000000142108547152020037174224853515625},{"id_detalle":"67695","id_producto":"262","codigo":"WRA-7486","descripcion":"FILTRO AIRE CATERPILLAR 6I-2501","na_pedido":"3584","cantidad":1,"precio":38.35000000000000142108547152020037174224853515625,"total":38.35000000000000142108547152020037174224853515625},{"id_detalle":"67696","id_producto":"253","codigo":"WRA-7140","descripcion":"FILTRO AIRE FORD-FREIGHTLINER-VOLVO","na_pedido":"3584","cantidad":4,"precio":42.9500000000000028421709430404007434844970703125,"total":171.80000000000001136868377216160297393798828125},{"id_detalle":"67697","id_producto":"520","codigo":"WA-10228","descripcion":"FILTRO AIRE JEEP CHEROKEE LIBERTY  V6 3.7L 08-13 (FLEXIBLE)","na_pedido":"3594","cantidad":6,"precio":7.78000000000000024868995751603506505489349365234375,"total":46.67999999999999971578290569595992565155029296875}]},{"id":"62611","id_users":"49","rif":"C-J312069503","nombre_cliente":"PARTES REPUESTOS FILTROS, C.A","num_fact":"18666","num_control":"33961","fecha_contab":"2026-06-10","fecha_venc":"2026-06-10","valor_moneda":572.678400000000010550138540565967559814453125,"moneda":"USD","iva":310.1200000000000045474735088646411895751953125,"porcentaje_iva":16,"porcentaje_descuento":0,"descuento":0,"sub_total":1938.25,"total_fact":2248.3699999999998908606357872486114501953125,"visto":"Y","nota_credito":null,"DocumentLines":[{"id_detalle":"46755","id_producto":"935","codigo":"WPS-2904","descripcion":"FILTRO COMB\/SEPARADOR CAMIONETA KAICENE CHANGAN F70, FOTON VIEW DRENADOR M12 X 1,5H","na_pedido":"2864","cantidad":48,"precio":9.4000000000000003552713678800500929355621337890625,"total":451.19999999999998863131622783839702606201171875},{"id_detalle":"46756","id_producto":"89","codigo":"WCA-1581","descripcion":"FILTRO AIRE MACK 57MD26 Y 27","na_pedido":"3135","cantidad":4,"precio":48.2000000000000028421709430404007434844970703125,"total":192.80000000000001136868377216160297393798828125},{"id_detalle":"46757","id_producto":"91","codigo":"WCA-1588","descripcion":"FILTRO AIRE PRIMARIO FORD 5000, 7000, 8000 D1NN-9601-A","na_pedido":"3136","cantidad":4,"precio":19.60000000000000142108547152020037174224853515625,"total":78.400000000000005684341886080801486968994140625},{"id_detalle":"46758","id_producto":"613","codigo":"W-8944","descripcion":"FILTRO ACEITE IVECO STRALIS.   IVECO 2992544","na_pedido":"3140","cantidad":12,"precio":11.4900000000000002131628207280300557613372802734375,"total":137.8799999999999954525264911353588104248046875},{"id_detalle":"46759","id_producto":"603","codigo":"W-7003","descripcion":"FILTRO ACEITE SINOTRUK HOWO A-7","na_pedido":"3140","cantidad":12,"precio":8.5,"total":102},{"id_detalle":"46760","id_producto":"452","codigo":"WA-3901","descripcion":"FILTRO AIRE CHRYSLER JEEP CHEROKEE- RAM 2500 (94\/2004) WIX 46077","na_pedido":"3155","cantidad":6,"precio":5.5,"total":33},{"id_detalle":"46761","id_producto":"504","codigo":"WA-9332","descripcion":"FILTRO AIRE FORD EXPLORER 02-05, MERCURY WIX 42484","na_pedido":"3155","cantidad":6,"precio":7.37000000000000010658141036401502788066864013671875,"total":44.219999999999998863131622783839702606201171875},{"id_detalle":"46762","id_producto":"270","codigo":"WRA-8280","descripcion":"FILTRO AIRE IVECO DAILY 60-12   93828280","na_pedido":"3248","cantidad":6,"precio":17.550000000000000710542735760100185871124267578125,"total":105.2999999999999971578290569595992565155029296875},{"id_detalle":"46763","id_producto":"249","codigo":"WRA-5668","descripcion":"FILTRO AIRE IVECO TRUCKS DAILY 50-12.","na_pedido":"3248","cantidad":3,"precio":13.9000000000000003552713678800500929355621337890625,"total":41.7000000000000028421709430404007434844970703125},{"id_detalle":"46764","id_producto":"125","codigo":"WCA-258","descripcion":"FILTRO AIRE PRIMARIO JOHN DEERE, MASEY FERGUNSON","na_pedido":"3248","cantidad":4,"precio":14.5999999999999996447286321199499070644378662109375,"total":58.39999999999999857891452847979962825775146484375},{"id_detalle":"46765","id_producto":"2165","codigo":"WCA-2342 SY","descripcion":"FILTRO AIRE DONGFENG KENGRUN 210 (DFL1140B), FAW CA1053","na_pedido":"3344","cantidad":4,"precio":14,"total":56},{"id_detalle":"46766","id_producto":"179","codigo":"WCA-5364","descripcion":"FILTRO AIRE PRIMARIO IVECO EUROTRAKKER MOTOR CURSOR 13 - 41272211","na_pedido":"3363","cantidad":5,"precio":47.75,"total":238.75},{"id_detalle":"46767","id_producto":"180","codigo":"WCA-5364 SY","descripcion":"FILTRO AIRE SECUNDARIO IVECO EUROTRAKKER","na_pedido":"3363","cantidad":5,"precio":14.4000000000000003552713678800500929355621337890625,"total":72},{"id_detalle":"46768","id_producto":"951","codigo":"WCA-4342","descripcion":"FILTRO AIRE MASVEN MASPARRO","na_pedido":"3363","cantidad":2,"precio":59.2000000000000028421709430404007434844970703125,"total":118.400000000000005684341886080801486968994140625},{"id_detalle":"46769","id_producto":"1045","codigo":"WCH-2301","descripcion":"FILTRO ACEITE DONGFENG RICH 6 DI, M9T-60A L4, 2.3L","na_pedido":"3370","cantidad":12,"precio":6,"total":72},{"id_detalle":"46770","id_producto":"92","codigo":"WCA-1588 SY","descripcion":"FILTRO AIRE SECUNDARIO FORD 5000, 7000, 8000","na_pedido":"3370","cantidad":6,"precio":8.300000000000000710542735760100185871124267578125,"total":49.7999999999999971578290569595992565155029296875},{"id_detalle":"46771","id_producto":"1013","codigo":"WCA-5070 SY","descripcion":"FILTRO AIRE SECUNDARIO JAC HFC 1035","na_pedido":"3370","cantidad":4,"precio":9.5999999999999996447286321199499070644378662109375,"total":38.39999999999999857891452847979962825775146484375},{"id_detalle":"46772","id_producto":"1171","codigo":"WA-10234","descripcion":"FILTRO AIRE DONGFENG AEOLUS A60 2.0L, MOTOR MR20DE 12- (FLEXIBLE)","na_pedido":"3380","cantidad":6,"precio":8,"total":48}]},{"id":"62606","id_users":"49","rif":"C-J312069503","nombre_cliente":"PARTES REPUESTOS FILTROS, C.A","num_fact":"18665","num_control":"","fecha_contab":"2026-06-10","fecha_venc":"2026-06-10","valor_moneda":572.678400000000010550138540565967559814453125,"moneda":"USD","iva":162.3600000000000136424205265939235687255859375,"porcentaje_iva":16,"porcentaje_descuento":0,"descuento":0,"sub_total":1014.75,"total_fact":1177.109999999999899955582804977893829345703125,"visto":"Y","nota_credito":null,"DocumentLines":[{"id_detalle":"46742","id_producto":"1088","codigo":"WCH-38030","descripcion":"FILTRO ACEITE JAC HFC-1130 KR1 WP6240E32 EURO III L6; 6,8L 20-","na_pedido":"3392","cantidad":12,"precio":10,"total":120},{"id_detalle":"46743","id_producto":"1007","codigo":"WCA-6512 M","descripcion":"FILTRO AIRE CAMION MACK SERIE CL 653 57MD42M","na_pedido":"3394","cantidad":4,"precio":69,"total":276},{"id_detalle":"46744","id_producto":"79","codigo":"WCA-1544 SY","descripcion":"FILTRO AIRE ALLIS CHALMERS - MASSEY FERGUNSON, SECUNDARIO","na_pedido":"3398","cantidad":6,"precio":8.300000000000000710542735760100185871124267578125,"total":49.7999999999999971578290569595992565155029296875},{"id_detalle":"46745","id_producto":"616","codigo":"W-9911","descripcion":"FILTRO ACEITE HYUNDAI H1- KIA SORENTO - ISUZU NKR","na_pedido":"3398","cantidad":12,"precio":6.20000000000000017763568394002504646778106689453125,"total":74.400000000000005684341886080801486968994140625},{"id_detalle":"46746","id_producto":"1105","codigo":"WRA-4992","descripcion":"FILTRO AIRE PRIMARIO PARA AIRE BUS KAMAZ 4308.1","na_pedido":"3399","cantidad":2,"precio":32.35000000000000142108547152020037174224853515625,"total":64.7000000000000028421709430404007434844970703125},{"id_detalle":"46747","id_producto":"1106","codigo":"WRA-4992 SY","descripcion":"FILTRO AIRE SECUNDARIO PARA AIRE BUS KAMAZ 4308.1","na_pedido":"3399","cantidad":2,"precio":10.699999999999999289457264239899814128875732421875,"total":21.39999999999999857891452847979962825775146484375},{"id_detalle":"46748","id_producto":"89","codigo":"WCA-1581","descripcion":"FILTRO AIRE MACK 57MD26 Y 27","na_pedido":"3426","cantidad":4,"precio":48.2000000000000028421709430404007434844970703125,"total":192.80000000000001136868377216160297393798828125},{"id_detalle":"46749","id_producto":"23","codigo":"WCA-376","descripcion":"FILTRO AIRE RUSTICOS TOYOTA TODOS 42801","na_pedido":"3446","cantidad":2,"precio":10.5999999999999996447286321199499070644378662109375,"total":21.199999999999999289457264239899814128875732421875},{"id_detalle":"46750","id_producto":"984","codigo":"WCH-8066","descripcion":"FILTRO ACEITE. CHEVROLET EXZ. MOTOR ISUZU 6WF1","na_pedido":"3446","cantidad":8,"precio":12.050000000000000710542735760100185871124267578125,"total":96.400000000000005684341886080801486968994140625},{"id_detalle":"46751","id_producto":"1069","codigo":"WRA-8280 SY","descripcion":"FILTRO AIRE IVECO DAILY 60.12 MOTOR 8140.43 2.8L L4 05-07.","na_pedido":"3448","cantidad":2,"precio":7,"total":14},{"id_detalle":"46752","id_producto":"1210","codigo":"WCA-6319","descripcion":"FILTRO AIRE EXCAVADORAS CATERPILLAR MODELO 5080","na_pedido":"3448","cantidad":1,"precio":56.9500000000000028421709430404007434844970703125,"total":56.9500000000000028421709430404007434844970703125},{"id_detalle":"46753","id_producto":"1428","codigo":"WCA-6319 SY","descripcion":"FILTRO AIRE EXCAVADORAS CATERPILLAR MODELO 5080","na_pedido":"3448","cantidad":1,"precio":27.10000000000000142108547152020037174224853515625,"total":27.10000000000000142108547152020037174224853515625}]},{"id":"40851","id_users":"49","rif":"C-J312069503","nombre_cliente":"PARTES REPUESTOS FILTROS, C.A","num_fact":"18483","num_control":"","fecha_contab":"2026-05-22","fecha_venc":"2026-05-22","valor_moneda":526.86940000000004147295840084552764892578125,"moneda":"USD","iva":105.695999999999997953636921010911464691162109375,"porcentaje_iva":16,"porcentaje_descuento":0,"descuento":0,"sub_total":660.6000000000000227373675443232059478759765625,"total_fact":766.296000000000049112713895738124847412109375,"visto":"Y","nota_credito":null,"DocumentLines":[{"id_detalle":"39159","id_producto":"584","codigo":"W-47","descripcion":"FILTRO ACEITE CASE JHON DEERE (AR-43634)","na_pedido":"3016","cantidad":8,"precio":13.800000000000000710542735760100185871124267578125,"total":110.400000000000005684341886080801486968994140625},{"id_detalle":"39160","id_producto":"648","codigo":"WP-3401","descripcion":"FILTRO COMBUSTIBLE CARRIER-TRANSSICOLD. CON DRENADOR M8 X 1,5H","na_pedido":"3135","cantidad":24,"precio":7.5999999999999996447286321199499070644378662109375,"total":182.400000000000005684341886080801486968994140625},{"id_detalle":"39161","id_producto":"703","codigo":"W-2010","descripcion":"FILTRO ACEITE CHERY ORINOCO 1.8L 11-16, FOTON AUMARK TX, E","na_pedido":"3248","cantidad":12,"precio":7.25,"total":87},{"id_detalle":"39162","id_producto":"982","codigo":"WPS-3409","descripcion":"FILTRO COMB\/SEPARADOR CAMIONES JAC HFC1061, ROSCA M20 *1,5, CON DRENADOR M12 X 1,25H","na_pedido":"3248","cantidad":12,"precio":7.5999999999999996447286321199499070644378662109375,"total":91.2000000000000028421709430404007434844970703125},{"id_detalle":"39163","id_producto":"2215","codigo":"W-4121","descripcion":"FILTRO DE ACEITE SINOTRUK BOLDEN S6, S7, S9 2.0L","na_pedido":"3314","cantidad":12,"precio":7.54999999999999982236431605997495353221893310546875,"total":90.599999999999994315658113919198513031005859375},{"id_detalle":"39164","id_producto":"1124","codigo":"WP-5706","descripcion":"FILTRO COMBUSTIBLE JAC HFC-1063","na_pedido":"3314","cantidad":6,"precio":16.5,"total":99}]},{"id":"40850","id_users":"49","rif":"C-J312069503","nombre_cliente":"PARTES REPUESTOS FILTROS, C.A","num_fact":"18482","num_control":"","fecha_contab":"2026-05-22","fecha_venc":"2026-05-22","valor_moneda":526.86940000000004147295840084552764892578125,"moneda":"USD","iva":161.34080000000000154614099301397800445556640625,"porcentaje_iva":16,"porcentaje_descuento":0,"descuento":0,"sub_total":1008.3799999999999954525264911353588104248046875,"total_fact":1169.7208000000000538420863449573516845703125,"visto":"Y","nota_credito":null,"DocumentLines":[{"id_detalle":"39144","id_producto":"1077","codigo":"WCA-7070","descripcion":"FILTRO AIRE PRIMARIO IVECO STRALIS 740S42, MOTOR F3BE0681 CURSOR 13, 12.9L, 06-08","na_pedido":"3155","cantidad":2,"precio":51.7000000000000028421709430404007434844970703125,"total":103.400000000000005684341886080801486968994140625},{"id_detalle":"39145","id_producto":"773","codigo":"WCA-7111","descripcion":"FILTRO AIRE NEW HOLLAND 7630 - IVECO- JOHN DEERE","na_pedido":"3155","cantidad":3,"precio":17.800000000000000710542735760100185871124267578125,"total":53.39999999999999857891452847979962825775146484375},{"id_detalle":"39146","id_producto":"1230","codigo":"WA-167","descripcion":"FILTRO AIRE ENCAVA E-VAN TOANO 16-","na_pedido":"3155","cantidad":6,"precio":6,"total":36},{"id_detalle":"39147","id_producto":"285","codigo":"WRA-9246","descripcion":"FILTRO AIRE THERMO KING ENCAVA 01-, MONTACARGAS CLARK, TOYOTA SERIE 6","na_pedido":"3155","cantidad":4,"precio":11,"total":44},{"id_detalle":"39148","id_producto":"1001","codigo":"WRA-1050 SY","descripcion":"FILTRO AIRE SINOTRUCK HOWO A-7","na_pedido":"3169","cantidad":4,"precio":9,"total":36},{"id_detalle":"39149","id_producto":"287","codigo":"WRA-9269","descripcion":"FILTRO AIRE CHEVROLET EXPRESS CARGO VAN","na_pedido":"3248","cantidad":4,"precio":16.89999999999999857891452847979962825775146484375,"total":67.599999999999994315658113919198513031005859375},{"id_detalle":"39150","id_producto":"772","codigo":"WCK-7206","descripcion":"KIT FILTRO ACEITE MITSUBISHI CANTER FV 517","na_pedido":"3248","cantidad":8,"precio":18.800000000000000710542735760100185871124267578125,"total":150.400000000000005684341886080801486968994140625},{"id_detalle":"39151","id_producto":"986","codigo":"WA-11895","descripcion":"FILTRO AIRE TOYOTA TUNDRA 13-21, SEQUOIA 14-21","na_pedido":"3258","cantidad":6,"precio":10.2400000000000002131628207280300557613372802734375,"total":61.43999999999999772626324556767940521240234375},{"id_detalle":"39152","id_producto":"514","codigo":"WA-10092","descripcion":"FILTRO AIRE FORD FUSION 3.0L 07-09 (FLEXIBLE)","na_pedido":"3258","cantidad":6,"precio":4.4900000000000002131628207280300557613372802734375,"total":26.940000000000001278976924368180334568023681640625},{"id_detalle":"39153","id_producto":"1247","codigo":"WRAK-2100","descripcion":"KIT DE FILTROS PARA AIRE SINOTRUCK HOMAN ZZ1168F 5TON. MOTOR CUMMINS ISF38L TURBO EURO III, MOTOR YC4E160-33 YUCHAI 4.3L","na_pedido":"3271","cantidad":3,"precio":25,"total":75},{"id_detalle":"39154","id_producto":"1232","codigo":"WCH-2062","descripcion":"FILTRO DE ACAITE FORD BRONCO 2,7L 21- (ELEMENTO)","na_pedido":"3273","cantidad":12,"precio":3.600000000000000088817841970012523233890533447265625,"total":43.2000000000000028421709430404007434844970703125},{"id_detalle":"39155","id_producto":"1229","codigo":"WCH-1243","descripcion":"FILTRO DE ACEITE FORD TERRITORY 1,8L 19- (ELEMENTO)","na_pedido":"3273","cantidad":6,"precio":3.29999999999999982236431605997495353221893310546875,"total":19.800000000000000710542735760100185871124267578125},{"id_detalle":"39156","id_producto":"1248","codigo":"WRAK-5672","descripcion":"KIT FILTRO AIRE XCMG CARGADOR LW800K, LW900KN, DONGFENG TIANLONG\/BUSES YUTONG\/MOTONIVELADORA GR300 X","na_pedido":"3297","cantidad":3,"precio":60,"total":180},{"id_detalle":"39157","id_producto":"166","codigo":"WCA-5070","descripcion":"FILTRO AIRE CAMION NPR MOTOR ISUZU 4BDI SIN TURBO, JAC HFC 1035","na_pedido":"3314","cantidad":4,"precio":17.449999999999999289457264239899814128875732421875,"total":69.7999999999999971578290569595992565155029296875},{"id_detalle":"39158","id_producto":"961","codigo":"WCA-1727","descripcion":"FILTRO AIRE FOTON VAN VIEW C2 2.8L MOTOR 4JB1T ISUZU","na_pedido":"3314","cantidad":3,"precio":13.800000000000000710542735760100185871124267578125,"total":41.39999999999999857891452847979962825775146484375}]},{"id":"20545","id_users":"49","rif":"C-J312069503","nombre_cliente":"PARTES REPUESTOS FILTROS, C.A","num_fact":"18267","num_control":"33492","fecha_contab":"2026-04-30","fecha_venc":"2026-04-30","valor_moneda":487.1191999999999779902282170951366424560546875,"moneda":"USD","iva":122.12479999999999336068867705762386322021484375,"porcentaje_iva":16,"porcentaje_descuento":0,"descuento":0,"sub_total":763.279999999999972715158946812152862548828125,"total_fact":885.404800000000022919266484677791595458984375,"visto":"Y","nota_credito":null,"DocumentLines":[{"id_detalle":"30923","id_producto":"642","codigo":"WP-1654","descripcion":"FILTRO ACEITE GREESEN. FORD CONNB91.","na_pedido":"2785","cantidad":12,"precio":5.79999999999999982236431605997495353221893310546875,"total":69.599999999999994315658113919198513031005859375},{"id_detalle":"30924","id_producto":"375","codigo":"WC-1721","descripcion":"FILTRO ACEITE JOHN DEERE AR-75603 AR-75601, SUSTITUYE WCH-331-E","na_pedido":"2785","cantidad":6,"precio":4.95000000000000017763568394002504646778106689453125,"total":29.699999999999999289457264239899814128875732421875},{"id_detalle":"30925","id_producto":"5","codigo":"WCA-146","descripcion":"FILTRO AIRE RENAULT R4.VALIANT 64\/77 .DART. ASPEN","na_pedido":"2785","cantidad":6,"precio":4,"total":24},{"id_detalle":"30926","id_producto":"1116","codigo":"WPS-10975","descripcion":"FILTRO COMB\/SEPARADOR (SERIE WT-120) BASE M18X1.5","na_pedido":"2943","cantidad":12,"precio":8.800000000000000710542735760100185871124267578125,"total":105.599999999999994315658113919198513031005859375},{"id_detalle":"30927","id_producto":"775","codigo":"WRA-30212 SY","descripcion":"FILTRO AIRE SECUNDARIO NEW HOLLAND TS6030, JOHN DEERE 5605, 5705","na_pedido":"2943","cantidad":10,"precio":8.300000000000000710542735760100185871124267578125,"total":83},{"id_detalle":"30928","id_producto":"375","codigo":"WC-1721","descripcion":"FILTRO ACEITE JOHN DEERE AR-75603 AR-75601, SUSTITUYE WCH-331-E","na_pedido":"3004","cantidad":12,"precio":4.95000000000000017763568394002504646778106689453125,"total":59.39999999999999857891452847979962825775146484375},{"id_detalle":"30929","id_producto":"969","codigo":"WCH-5199","descripcion":"FILTRO ACEITE MAZ CAMION MASPARRO (643008) MV-27V01, MV-26Q01, MV-26C01 MOTOR 14.9L YMZ-7511.10","na_pedido":"3007","cantidad":12,"precio":9.6500000000000003552713678800500929355621337890625,"total":115.7999999999999971578290569595992565155029296875},{"id_detalle":"30930","id_producto":"290","codigo":"WRA-9869","descripcion":"FILTRO AIRE MACK VISION WIX 42808 MACK 57MD320M","na_pedido":"3035","cantidad":2,"precio":41.14999999999999857891452847979962825775146484375,"total":82.2999999999999971578290569595992565155029296875},{"id_detalle":"30931","id_producto":"950","codigo":"WRA-1930","descripcion":"FILTRO AIRE FOTON AUMARK E, S BJ1088 5 TON MOTOR CUMMINS F3.8s3141 3.8L","na_pedido":"3038","cantidad":2,"precio":16.75,"total":33.5},{"id_detalle":"30932","id_producto":"936","codigo":"WFA-5693","descripcion":"FILTRO AIRE SELLADO IVECO - FORD - FREIGHTLINER - MERCEDES","na_pedido":"3038","cantidad":6,"precio":18.730000000000000426325641456060111522674560546875,"total":112.3799999999999954525264911353588104248046875},{"id_detalle":"30933","id_producto":"5","codigo":"WCA-146","descripcion":"FILTRO AIRE RENAULT R4.VALIANT 64\/77 .DART. ASPEN","na_pedido":"3097","cantidad":12,"precio":4,"total":48}]},{"id":"15768","id_users":"49","rif":"C-J312069503","nombre_cliente":"PARTES REPUESTOS FILTROS, C.A","num_fact":"18266","num_control":"33491","fecha_contab":"2026-04-30","fecha_venc":"2026-04-30","valor_moneda":487.1191999999999779902282170951366424560546875,"moneda":"USD","iva":48.768000000000000682121026329696178436279296875,"porcentaje_iva":16,"porcentaje_descuento":0,"descuento":0,"sub_total":304.80000000000001136868377216160297393798828125,"total_fact":353.567999999999983629095368087291717529296875,"visto":"Y","nota_credito":null,"DocumentLines":[{"id_detalle":"29472","id_producto":"563","codigo":"W-3612","descripcion":"FILTRO ACEITE CUMMINS. DETROIT DIESEL.","na_pedido":"3135","cantidad":12,"precio":13.5,"total":162},{"id_detalle":"29473","id_producto":"1231","codigo":"WCH-11673","descripcion":"FILTRO DE ACEITE HUNTER F70 SC1031PACS6 MOTOR GW4D320M","na_pedido":"3135","cantidad":12,"precio":2.79999999999999982236431605997495353221893310546875,"total":33.60000000000000142108547152020037174224853515625},{"id_detalle":"29474","id_producto":"375","codigo":"WC-1721","descripcion":"FILTRO ACEITE JOHN DEERE AR-75603 AR-75601, SUSTITUYE WCH-331-E","na_pedido":"3136","cantidad":12,"precio":4.95000000000000017763568394002504646778106689453125,"total":59.39999999999999857891452847979962825775146484375},{"id_detalle":"29475","id_producto":"92","codigo":"WCA-1588 SY","descripcion":"FILTRO AIRE SECUNDARIO FORD 5000, 7000, 8000","na_pedido":"3136","cantidad":6,"precio":8.300000000000000710542735760100185871124267578125,"total":49.7999999999999971578290569595992565155029296875}]},{"id":"9749","id_users":"49","rif":"C-J312069503","nombre_cliente":"PARTES REPUESTOS FILTROS, C.A","num_fact":"18189","num_control":"33408","fecha_contab":"2026-04-24","fecha_venc":"2026-04-24","valor_moneda":483.869500000000016370904631912708282470703125,"moneda":"USD","iva":193.156800000000004047251422889530658721923828125,"porcentaje_iva":16,"porcentaje_descuento":0,"descuento":0,"sub_total":1207.23000000000001818989403545856475830078125,"total_fact":1400.386799999999993815436027944087982177734375,"visto":"N","nota_credito":null,"DocumentLines":[{"id_detalle":"27075","id_producto":"490","codigo":"WA-8004","descripcion":"FILTRO AIRE FORD FORTALEZA, MUSTANG V8, 4.6 Lt (99-05) WIX 46418","na_pedido":"3022","cantidad":2,"precio":13.800000000000000710542735760100185871124267578125,"total":27.60000000000000142108547152020037174224853515625},{"id_detalle":"27076","id_producto":"595","codigo":"W-6357","descripcion":"FILTRO ACEITE TOYOTA COASTER 2007","na_pedido":"3035","cantidad":12,"precio":8.800000000000000710542735760100185871124267578125,"total":105.599999999999994315658113919198513031005859375},{"id_detalle":"27077","id_producto":"1008","codigo":"WRA-5534","descripcion":"FILTRO AIRE BUS MARCOPOLO 60PTOS CHASIS MERCEDES BENZSW O-500RSD MOTOR OM457 LA02, GRUAS LIEBHERR","na_pedido":"3035","cantidad":2,"precio":36.25,"total":72.5},{"id_detalle":"27078","id_producto":"1184","codigo":"WC-634","descripcion":"FILTRO COMBUSTIBLE PRIMARIO SINOTRUK BOLDEN S6, S7, S9","na_pedido":"3038","cantidad":6,"precio":11,"total":66},{"id_detalle":"27079","id_producto":"950","codigo":"WRA-1930","descripcion":"FILTRO AIRE FOTON AUMARK E, S BJ1088 5 TON MOTOR CUMMINS F3.8s3141 3.8L","na_pedido":"3038","cantidad":2,"precio":16.75,"total":33.5},{"id_detalle":"27080","id_producto":"750","codigo":"WRA-8193","descripcion":"FILTRO AIRE FREIGHTLINER MOTOR CATERPILLAR 3126 ( 95-04)","na_pedido":"3062","cantidad":3,"precio":34.0499999999999971578290569595992565155029296875,"total":102.150000000000005684341886080801486968994140625},{"id_detalle":"27081","id_producto":"668","codigo":"WP-7624","descripcion":"FILTRO COMBUSTIBLE CAMIONES SCANIA","na_pedido":"3083","cantidad":12,"precio":6.20000000000000017763568394002504646778106689453125,"total":74.400000000000005684341886080801486968994140625},{"id_detalle":"27082","id_producto":"674","codigo":"WP-8049","descripcion":"FILTRO COMBUSTIBLE MACK PRIMARIO 483GB 470M","na_pedido":"3088","cantidad":12,"precio":11.3300000000000000710542735760100185871124267578125,"total":135.960000000000007958078640513122081756591796875},{"id_detalle":"27083","id_producto":"1089","codigo":"WRA-3538","descripcion":"FILTRO AIRE PRIM. HITACHI, CHEVROLET FSR 13-,FVR 24-, FTR5.2L MOTOR 4HK1-T, FILTRO AIRE ISUZU FVR FORWARD 12TON. FVR34UL-MDN NACIONAL","na_pedido":"3088","cantidad":1,"precio":31.10000000000000142108547152020037174224853515625,"total":31.10000000000000142108547152020037174224853515625},{"id_detalle":"27084","id_producto":"1164","codigo":"WC-9262","descripcion":"FILTRO COMBUSTIBLE FREIGHTLINER M2-106 MOTOR MERCEDES","na_pedido":"3062","cantidad":6,"precio":6.67999999999999971578290569595992565155029296875,"total":40.0799999999999982946974341757595539093017578125},{"id_detalle":"27085","id_producto":"807","codigo":"WP-9257","descripcion":"FILTRO COMB\/SEPARADOR, (WPS-8185\/WPS-9257 CON DRENADOR M12 X 1,5)H","na_pedido":"3062","cantidad":12,"precio":8.8499999999999996447286321199499070644378662109375,"total":106.2000000000000028421709430404007434844970703125},{"id_detalle":"27086","id_producto":"947","codigo":"WRA-2640","descripcion":"FILTRO AIRE PRIMARIO FOTON BJ1166 12TON 6.7L MOTOR CUMMINS ISDE245-30, BJ5166, YUTONG 8 MTS","na_pedido":"3062","cantidad":2,"precio":31.050000000000000710542735760100185871124267578125,"total":62.10000000000000142108547152020037174224853515625},{"id_detalle":"27087","id_producto":"1067","codigo":"WP-10969","descripcion":"FILTRO ACEITE HIDRAULICO FORD - NEW HOLLAND - CASE","na_pedido":"3062","cantidad":6,"precio":26.839999999999999857891452847979962825775146484375,"total":161.039999999999992041921359486877918243408203125},{"id_detalle":"27088","id_producto":"2164","codigo":"WCA-2342","descripcion":"FILTRO AIRE DONGFENG KINGRUN 210 (DFL1140B), FAW CA1053","na_pedido":"3062","cantidad":4,"precio":30,"total":120},{"id_detalle":"27089","id_producto":"1421","codigo":"WC-509","descripcion":"FILTRO DE COMBUSTIBLE FORD RANGER 3,2L, 2,2L 21-","na_pedido":"3083","cantidad":6,"precio":11.5,"total":69}]},{"id":"6322","id_users":"49","rif":"C-J312069503","nombre_cliente":"PARTES REPUESTOS FILTROS, C.A","num_fact":"18055","num_control":"","fecha_contab":"2026-04-09","fecha_venc":"2026-04-09","valor_moneda":475.958300000000008367351256310939788818359375,"moneda":"USD","iva":319.10399999999998499333742074668407440185546875,"porcentaje_iva":16,"porcentaje_descuento":0,"descuento":0,"sub_total":1994.40000000000009094947017729282379150390625,"total_fact":2313.5039999999999054125510156154632568359375,"visto":"Y","nota_credito":null,"DocumentLines":[{"id_detalle":"25096","id_producto":"618","codigo":"WG-1101","descripcion":"FILTRO DE GASOLINA SURTIDORES DE COMBUSTIBLE PAPEL SENCILLO","na_pedido":"2785","cantidad":12,"precio":5.3499999999999996447286321199499070644378662109375,"total":64.2000000000000028421709430404007434844970703125},{"id_detalle":"25097","id_producto":"415","codigo":"WC-4844","descripcion":"FILTRO DE COMBUSTIBLE INTERNATIONAL  (133736CI)","na_pedido":"2950","cantidad":18,"precio":5,"total":90},{"id_detalle":"25098","id_producto":"400","codigo":"WCH-3584","descripcion":"FILTRO ACEITE CATERPILLAR MOTOR MARINO 3508","na_pedido":"2950","cantidad":4,"precio":30,"total":120},{"id_detalle":"25099","id_producto":"953","codigo":"WPS-10812","descripcion":"FILTRO COMB\/SEPARADOR FOTON AUMARK 2.5T, 3.0TON DRENADOR M8X1,25","na_pedido":"2977","cantidad":150,"precio":11.03999999999999914734871708787977695465087890625,"total":1656},{"id_detalle":"25100","id_producto":"618","codigo":"WG-1101","descripcion":"FILTRO DE GASOLINA SURTIDORES DE COMBUSTIBLE PAPEL SENCILLO","na_pedido":"2977","cantidad":12,"precio":5.3499999999999996447286321199499070644378662109375,"total":64.2000000000000028421709430404007434844970703125}]},{"id":"1830","id_users":"49","rif":"C-J312069503","nombre_cliente":"PARTES REPUESTOS FILTROS, C.A","num_fact":"17928","num_control":"33136","fecha_contab":"2026-03-20","fecha_venc":"2026-03-20","valor_moneda":455.25470000000001391526893712580204010009765625,"moneda":"USD","iva":263.3663999999999987267074175179004669189453125,"porcentaje_iva":16,"porcentaje_descuento":0,"descuento":0,"sub_total":1646.0399999999999636202119290828704833984375,"total_fact":1909.406400000000076033757068216800689697265625,"visto":"Y","nota_credito":null,"DocumentLines":[{"id_detalle":"10700","id_producto":"772","codigo":"WCK-7206","descripcion":"KIT FILTRO ACEITE MITSUBISHI CANTER FV 517","na_pedido":"2785","cantidad":8,"precio":18.800000000000000710542735760100185871124267578125,"total":150.400000000000005684341886080801486968994140625},{"id_detalle":"10701","id_producto":"1248","codigo":"WRAK-5672","descripcion":"KIT FILTRO AIRE XCMG CARGADOR LW800K, LW900KN, DONGFENG TIANLONG\/BUSES YUTONG\/MOTONIVELADORA GR300 X","na_pedido":"2785","cantidad":3,"precio":60,"total":180},{"id_detalle":"10702","id_producto":"979","codigo":"WRF-4023","descripcion":"WEB REFRIGERANTE GOLD AMARILLO 3,78 L","na_pedido":"2785","cantidad":4,"precio":28.949999999999999289457264239899814128875732421875,"total":115.7999999999999971578290569595992565155029296875},{"id_detalle":"10703","id_producto":"400","codigo":"WCH-3584","descripcion":"FILTRO ACEITE CATERPILLAR MOTOR MARINO 3508","na_pedido":"2785","cantidad":4,"precio":30,"total":120},{"id_detalle":"10704","id_producto":"935","codigo":"WPS-2904","descripcion":"FILTRO COMB\/SEPARADOR CAMIONETA KAICENE CHANGAN F70, FOTON VIEW DRENADOR M12 X 1,5H","na_pedido":"2789","cantidad":12,"precio":9.4000000000000003552713678800500929355621337890625,"total":112.7999999999999971578290569595992565155029296875},{"id_detalle":"10705","id_producto":"210","codigo":"WCA-7178 SY","descripcion":"FILTRO AIRE COMPRESORES ATLAS COPCO, VM, PEGASO 1217, TECTOR, SECUNDARIO","na_pedido":"2824","cantidad":4,"precio":8.300000000000000710542735760100185871124267578125,"total":33.2000000000000028421709430404007434844970703125},{"id_detalle":"10706","id_producto":"183","codigo":"WCA-546","descripcion":"FILTRO AIRE PRIMARIO ALLIS CHALMERS, FORD CARGO 1617 5.9L 684732-1","na_pedido":"2824","cantidad":1,"precio":25.699999999999999289457264239899814128875732421875,"total":25.699999999999999289457264239899814128875732421875},{"id_detalle":"10707","id_producto":"184","codigo":"WCA-546 SY","descripcion":"FILTRO AIRE SECUNDARIO ALLIS CHALMERS 662608,","na_pedido":"2824","cantidad":1,"precio":16.10000000000000142108547152020037174224853515625,"total":16.10000000000000142108547152020037174224853515625},{"id_detalle":"10708","id_producto":"363","codigo":"WC-1173","descripcion":"FILTRO COMBUSTIBLE ALLIS CHALMERS, CASE, DETROIT DIESEL","na_pedido":"2876","cantidad":24,"precio":3.45000000000000017763568394002504646778106689453125,"total":82.7999999999999971578290569595992565155029296875},{"id_detalle":"10709","id_producto":"364","codigo":"WC-1174","descripcion":"FILTRO COMBUSTIBLE ALLIS CHALMER,DETROIT,EUCLID GM ACTP-553","na_pedido":"2876","cantidad":20,"precio":3.5,"total":70},{"id_detalle":"10710","id_producto":"641","codigo":"WP-1506","descripcion":"FILTRO COMBUSTIBLE MITSUBISHI ME150631","na_pedido":"2876","cantidad":24,"precio":9.0099999999999997868371792719699442386627197265625,"total":216.240000000000009094947017729282379150390625},{"id_detalle":"10711","id_producto":"1059","codigo":"WPS-421","descripcion":"FILTRO COMB\/SEPARADOR HOWO T5G MC07.24-30 (UN DRENAJE)","na_pedido":"2879","cantidad":12,"precio":16.469999999999998863131622783839702606201171875,"total":197.6399999999999863575794734060764312744140625},{"id_detalle":"10712","id_producto":"1185","codigo":"WCH-1160","descripcion":"FILTRO ACEITE HAVAL H6, JOLION, AEOLUS AX7 PRO, 1.5L TURBO, MOTOR 5G06, 20-","na_pedido":"2884","cantidad":12,"precio":2.75,"total":33},{"id_detalle":"10713","id_producto":"790","codigo":"W-8476","descripcion":"FILTRO ACEITE  INGERSOLL RAND - JOHN DEERE","na_pedido":"2891","cantidad":12,"precio":11.5299999999999993605115378159098327159881591796875,"total":138.3600000000000136424205265939235687255859375},{"id_detalle":"10714","id_producto":"993","codigo":"WRA-10982","descripcion":"FILTRO AIRE PRIMARIO NEW HOLLAN T3000, SERIES EC25,EC35,EC45","na_pedido":"2891","cantidad":2,"precio":11,"total":22},{"id_detalle":"10715","id_producto":"1083","codigo":"WRA-10982 SY","descripcion":"FILTRO AIRE SECUNDARIO NEW HOLLAND T3000, SERIES EC25,EC35,EC45","na_pedido":"2891","cantidad":2,"precio":6,"total":12},{"id_detalle":"10716","id_producto":"400","codigo":"WCH-3584","descripcion":"FILTRO ACEITE CATERPILLAR MOTOR MARINO 3508","na_pedido":"2891","cantidad":4,"precio":30,"total":120}]},{"id":"1799","id_users":"49","rif":"C-J312069503","nombre_cliente":"PARTES REPUESTOS FILTROS, C.A","num_fact":"17915","num_control":"33124","fecha_contab":"2026-03-20","fecha_venc":"2026-03-20","valor_moneda":455.25470000000001391526893712580204010009765625,"moneda":"USD","iva":27.93599999999999994315658113919198513031005859375,"porcentaje_iva":16,"porcentaje_descuento":0,"descuento":0,"sub_total":174.599999999999994315658113919198513031005859375,"total_fact":202.53600000000000136424205265939235687255859375,"visto":"Y","nota_credito":null,"DocumentLines":[{"id_detalle":"10461","id_producto":"532","codigo":"W-16","descripcion":"FILTRO ACEITE FIAT REGATA, UNO (CARBURADO) FORD SIERRA.WRANGLER 6CIL, DODGE RAM","na_pedido":"","cantidad":12,"precio":6.04999999999999982236431605997495353221893310546875,"total":72.599999999999994315658113919198513031005859375},{"id_detalle":"10462","id_producto":"692","codigo":"WPS-8021","descripcion":"FILTRO COMBUSTIBLE HOWO A-7  (VG1540080211) PARA SENSOR M36 X  1,5","na_pedido":"","cantidad":6,"precio":17,"total":102}]},{"id":"484","id_users":"49","rif":"C-J312069503","nombre_cliente":"PARTES REPUESTOS FILTROS, C.A","num_fact":"17850","num_control":"","fecha_contab":"2026-03-13","fecha_venc":"2026-03-13","valor_moneda":443.2586999999999761712388135492801666259765625,"moneda":"USD","iva":50.1024000000000029331204132176935672760009765625,"porcentaje_iva":16,"porcentaje_descuento":0,"descuento":0,"sub_total":313.1399999999999863575794734060764312744140625,"total_fact":363.2423999999999750798451714217662811279296875,"visto":"Y","nota_credito":null,"DocumentLines":[{"id_detalle":"2411","id_producto":"587","codigo":"W-4798","descripcion":"FILTRO ACEITE VOLVO. CASE. FORD.CAMION JAC","na_pedido":"2785","cantidad":6,"precio":8.1899999999999995026200849679298698902130126953125,"total":49.1400000000000005684341886080801486968994140625},{"id_detalle":"2412","id_producto":"1103","codigo":"WCA-9601AA","descripcion":"FILTRO AIRE CAMION JMC N720 CARRING 2.8L 17-","na_pedido":"2813","cantidad":4,"precio":12,"total":48},{"id_detalle":"2413","id_producto":"209","codigo":"WCA-7178","descripcion":"FILTRO AIRE COMPRESORES ATLAS COPCO, VM, PEGASO 1217, TECTOR","na_pedido":"2824","cantidad":4,"precio":33.25,"total":133},{"id_detalle":"2414","id_producto":"281","codigo":"WRA-8737 SY","descripcion":"FILTRO AIRE SECUNDARIO CATERPILLAR SERIE 200, 400, 4300","na_pedido":"2864","cantidad":10,"precio":6.9000000000000003552713678800500929355621337890625,"total":69},{"id_detalle":"2415","id_producto":"1061","codigo":"WRA-9874","descripcion":"FILTRO AIRE RETROEXCAVADORAS CASE 580L MOTOR CUMMINS 4B3.9,580SL,580M,580L,590L,590SL","na_pedido":"2864","cantidad":1,"precio":14,"total":14}]},{"id":"438","id_users":"49","rif":"C-J312069503","nombre_cliente":"PARTES REPUESTOS FILTROS, C.A","num_fact":"17788","num_control":"32994","fecha_contab":"2026-03-09","fecha_venc":"2026-03-09","valor_moneda":433.16640000000001009539118967950344085693359375,"moneda":"USD","iva":30.182400000000001227817847393453121185302734375,"porcentaje_iva":16,"porcentaje_descuento":0,"descuento":0,"sub_total":188.6399999999999863575794734060764312744140625,"total_fact":218.822399999999987585397320799529552459716796875,"visto":"N","nota_credito":null,"DocumentLines":[{"id_detalle":"1866","id_producto":"1086","codigo":"WCH-7092","descripcion":"FILTRO ACEITE FLUJO TOTAL MITSUBISHI CANTER FV517","na_pedido":"2819","cantidad":12,"precio":10.7200000000000006394884621840901672840118408203125,"total":128.6399999999999863575794734060764312744140625},{"id_detalle":"1867","id_producto":"1114","codigo":"WA-5405","descripcion":"FILTRO AIRE MAXUS VAN V80 2.5L, 10-","na_pedido":"2819","cantidad":6,"precio":10,"total":60}]},{"id":"423","id_users":"49","rif":"C-J312069503","nombre_cliente":"PARTES REPUESTOS FILTROS, C.A","num_fact":"17767","num_control":"32972","fecha_contab":"2026-03-06","fecha_venc":"2026-03-06","valor_moneda":431.0113000000000056388671509921550750732421875,"moneda":"USD","iva":109.8719999999999998863131622783839702606201171875,"porcentaje_iva":-10,"porcentaje_descuento":0,"descuento":0,"sub_total":686.700000000000045474735088646411895751953125,"total_fact":796.5720000000000027284841053187847137451171875,"visto":"N","nota_credito":null,"DocumentLines":[{"id_detalle":"1722","id_producto":"589","codigo":"W-49","descripcion":"FILTRO ACEITE MACK. KODIAK. CATERPILLAR, VOLVO.","na_pedido":"2692","cantidad":12,"precio":13.160000000000000142108547152020037174224853515625,"total":157.919999999999987494447850622236728668212890625},{"id_detalle":"1723","id_producto":"1127","codigo":"WA-9711","descripcion":"FILTRO AIRE DONFENG RICH 6 FI, RICH 6 DI, RICH 7 2.3L ENGINE M9T, DONFENG  D1","na_pedido":"2692","cantidad":24,"precio":9,"total":216},{"id_detalle":"1724","id_producto":"331","codigo":"WC-196","descripcion":"FILTRO ACEITE IVECO, CATERPILLAR CAT9F-6742","na_pedido":"2692","cantidad":6,"precio":5.62999999999999989341858963598497211933135986328125,"total":33.780000000000001136868377216160297393798828125},{"id_detalle":"1725","id_producto":"1433","codigo":"WP-4506","descripcion":"FILTRO COMBUSTIBLE ABG,DEMAG,FORD,EXCAVADORAS HITACHI","na_pedido":"2692","cantidad":12,"precio":4,"total":48},{"id_detalle":"1726","id_producto":"1094","codigo":"WA-2311","descripcion":"FILTRO AIRE ENCAVA EP-1000 MOTORS CUMMINS ISF2.8 EURO II 2.8L, 20-","na_pedido":"2810","cantidad":12,"precio":8.949999999999999289457264239899814128875732421875,"total":107.400000000000005684341886080801486968994140625},{"id_detalle":"1727","id_producto":"1212","codigo":"WCS-19925","descripcion":"FILTRO COMBUSTIBLE FOTON TUNLAND C, ENCAVA EP-1000","na_pedido":"2810","cantidad":12,"precio":10.300000000000000710542735760100185871124267578125,"total":123.599999999999994315658113919198513031005859375}]},{"id":"422","id_users":"49","rif":"C-J312069503","nombre_cliente":"PARTES REPUESTOS FILTROS, C.A","num_fact":"17766","num_control":"32971","fecha_contab":"2026-03-06","fecha_venc":"2026-03-06","valor_moneda":431.0113000000000056388671509921550750732421875,"moneda":"USD","iva":255.9551999999999907231540419161319732666015625,"porcentaje_iva":16,"porcentaje_descuento":0,"descuento":0,"sub_total":1599.720000000000027284841053187847137451171875,"total_fact":1855.675199999999904321157373487949371337890625,"visto":"N","nota_credito":null,"DocumentLines":[{"id_detalle":"1705","id_producto":"1127","codigo":"WA-9711","descripcion":"FILTRO AIRE DONFENG RICH 6 FI, RICH 6 DI, RICH 7 2.3L ENGINE M9T, DONFENG  D1","na_pedido":"2784","cantidad":24,"precio":9,"total":216},{"id_detalle":"1706","id_producto":"1092","codigo":"WPS-9794","descripcion":"FILTRO COMBUSTIBLE\/SEPARADOR 33812 S3226P MERCEDES M2-106 M2-112","na_pedido":"2785","cantidad":6,"precio":17.6099999999999994315658113919198513031005859375,"total":105.659999999999996589394868351519107818603515625},{"id_detalle":"1707","id_producto":"1211","codigo":"WC-0L050","descripcion":"FILTRO COMBUSTIBLE MITSUBISHI L200 L4, 2.5L,A\u00d1O 16-22","na_pedido":"2785","cantidad":6,"precio":5.69000000000000039079850466805510222911834716796875,"total":34.1400000000000005684341886080801486968994140625},{"id_detalle":"1708","id_producto":"1088","codigo":"WCH-38030","descripcion":"FILTRO ACEITE JAC HFC-1130 KR1 WP6240E32 EURO III L6; 6,8L 20-","na_pedido":"2785","cantidad":12,"precio":10,"total":120},{"id_detalle":"1709","id_producto":"337","codigo":"WCH-238","descripcion":"FILTRO ACEITE CATERPILLAR (CAT 5S-485)","na_pedido":"2785","cantidad":12,"precio":8.25,"total":99},{"id_detalle":"1710","id_producto":"804","codigo":"WC-8220","descripcion":"FILTRO COMBUSTIBLE TOYOTA DYNA CON TURBO 2008","na_pedido":"2785","cantidad":12,"precio":6.5099999999999997868371792719699442386627197265625,"total":78.1200000000000045474735088646411895751953125},{"id_detalle":"1711","id_producto":"1030","codigo":"WC-10353","descripcion":"FILTRO COMBUSTIBLE MITSUBISHI L200 L4, 2.5L; A\u00d1O 11 al 15","na_pedido":"2785","cantidad":12,"precio":5.0999999999999996447286321199499070644378662109375,"total":61.2000000000000028421709430404007434844970703125},{"id_detalle":"1712","id_producto":"1087","codigo":"WCH-7093","descripcion":"FILTRO ACEITE  BY PASS MITSUBISHI CANTER FV 517","na_pedido":"2785","cantidad":6,"precio":9,"total":54},{"id_detalle":"1713","id_producto":"1148","codigo":"WCH-84000","descripcion":"FILTRO ACEITE FLUJO TOTAL HYUNDAI HD270, HD370, HD1000 12,9L, 06-09, D6CA-41 TURBO","na_pedido":"2785","cantidad":6,"precio":9,"total":54},{"id_detalle":"1714","id_producto":"11","codigo":"WCA-192","descripcion":"FILTRO AIRE MONTECARLO,PICK-UP 6CL. MALIBU,CAPRICE","na_pedido":"2785","cantidad":6,"precio":4.29999999999999982236431605997495353221893310546875,"total":25.800000000000000710542735760100185871124267578125},{"id_detalle":"1715","id_producto":"549","codigo":"W-2975","descripcion":"FILTRO ACEITE ISUZU 4BD1T (PRIM) EQ. WH-030.","na_pedido":"2785","cantidad":12,"precio":7.5999999999999996447286321199499070644378662109375,"total":91.2000000000000028421709430404007434844970703125},{"id_detalle":"1716","id_producto":"33","codigo":"WCA-2718","descripcion":"FILTRO AIRE FIAT SPACIO 81\/86. FIORINO 84\/86 UNIVERSAL","na_pedido":"2785","cantidad":6,"precio":3.79999999999999982236431605997495353221893310546875,"total":22.800000000000000710542735760100185871124267578125},{"id_detalle":"1717","id_producto":"779","codigo":"WP-8043","descripcion":"FILTRO COMB\/SEPARADOR IVECO TURBO DAILY KAICENE CHANGAN F70 DRENADOR M8 X 1,25","na_pedido":"2790","cantidad":24,"precio":7.20000000000000017763568394002504646778106689453125,"total":172.80000000000001136868377216160297393798828125},{"id_detalle":"1718","id_producto":"369","codigo":"WC-1191","descripcion":"FILTRO COMBUSTIBLE TIPO CAV JOHN DEERE, MASEY FERGUNSON, PERKINS","na_pedido":"2790","cantidad":12,"precio":3.79999999999999982236431605997495353221893310546875,"total":45.60000000000000142108547152020037174224853515625},{"id_detalle":"1719","id_producto":"370","codigo":"WC-1191-C","descripcion":"FILTRO COMBUSTIBLE TIPO CAV PEGASO SECUNDARIO ENASA 770-915","na_pedido":"2790","cantidad":12,"precio":4.70000000000000017763568394002504646778106689453125,"total":56.39999999999999857891452847979962825775146484375},{"id_detalle":"1720","id_producto":"658","codigo":"WP-4102","descripcion":"FILTRO COMBUSTIBLE FORD 7000,CASE, IVECO, DEUZT","na_pedido":"2797","cantidad":60,"precio":4.1500000000000003552713678800500929355621337890625,"total":249},{"id_detalle":"1721","id_producto":"1129","codigo":"WA-4700","descripcion":"FILTRO AIRE DONFENG GLORY 500 1,5L","na_pedido":"2801","cantidad":12,"precio":9.5,"total":114}]},{"id":"421","id_users":"49","rif":"C-J312069503","nombre_cliente":"PARTES REPUESTOS FILTROS, C.A","num_fact":"17765","num_control":"32970","fecha_contab":"2026-03-06","fecha_venc":"2026-03-06","valor_moneda":431.0113000000000056388671509921550750732421875,"moneda":"USD","iva":125.182400000000001227817847393453121185302734375,"porcentaje_iva":16,"porcentaje_descuento":0,"descuento":0,"sub_total":782.3899999999999863575794734060764312744140625,"total_fact":907.5724000000000160071067512035369873046875,"visto":"N","nota_credito":null,"DocumentLines":[{"id_detalle":"1693","id_producto":"992","codigo":"WRA-9244 SY","descripcion":"FILTRO AIRE SECUNDARIO CATERPILLAR 131-8821","na_pedido":"2785","cantidad":4,"precio":9.6500000000000003552713678800500929355621337890625,"total":38.60000000000000142108547152020037174224853515625},{"id_detalle":"1694","id_producto":"1018","codigo":"WCA-5503 SY","descripcion":"FILTRO AIRE SECUNDARIO DONGFENG DUOLIKA 5 TON,","na_pedido":"2785","cantidad":2,"precio":9.6500000000000003552713678800500929355621337890625,"total":19.300000000000000710542735760100185871124267578125},{"id_detalle":"1695","id_producto":"86","codigo":"WCA-1565","descripcion":"FILTRO AIRE JOHN DEERE, INTERNATIONAL","na_pedido":"2785","cantidad":3,"precio":19,"total":57},{"id_detalle":"1696","id_producto":"751","codigo":"WRA-5014","descripcion":"FILTRO AIRE MITSUBISHI CANTER 649 D","na_pedido":"2785","cantidad":6,"precio":13.6500000000000003552713678800500929355621337890625,"total":81.900000000000005684341886080801486968994140625},{"id_detalle":"1697","id_producto":"1008","codigo":"WRA-5534","descripcion":"FILTRO AIRE BUS MARCOPOLO 60PTOS CHASIS MERCEDES BENZSW O-500RSD MOTOR OM457 LA02, GRUAS LIEBHERR","na_pedido":"2785","cantidad":2,"precio":36.25,"total":72.5},{"id_detalle":"1698","id_producto":"1111","codigo":"WRA-3538 SY","descripcion":"FILTRO AIRE SECUNDARIO HITACHI, CHEVROLET FSR 13-,FVR 24-, FTR5.2L MOTOR 4HK1-T, FILTRO AIRE ISUZU FVR FORWARD 12TON. FVR34UL-MDN NACIONAL","na_pedido":"2785","cantidad":2,"precio":12,"total":24},{"id_detalle":"1699","id_producto":"144","codigo":"WCA-3281","descripcion":"FILTRO AIRE MERCEDES BENZ,VOLVO 7362224, PEGASO","na_pedido":"2785","cantidad":4,"precio":26.800000000000000710542735760100185871124267578125,"total":107.2000000000000028421709430404007434844970703125},{"id_detalle":"1700","id_producto":"1132","codigo":"WCA-5804","descripcion":"FILTRO AIRE TOYOTA COASTER 06-07  ( 17801-58040)","na_pedido":"2785","cantidad":2,"precio":21,"total":42},{"id_detalle":"1701","id_producto":"283","codigo":"WRA-9240","descripcion":"FILTRO AIRE MITSUBISHI FH-217,FK-615 BALDWIN RS-3731","na_pedido":"2785","cantidad":4,"precio":32.4500000000000028421709430404007434844970703125,"total":129.80000000000001136868377216160297393798828125},{"id_detalle":"1702","id_producto":"947","codigo":"WRA-2640","descripcion":"FILTRO AIRE PRIMARIO FOTON BJ1166 12TON 6.7L MOTOR CUMMINS ISDE245-30, BJ5166, YUTONG 8 MTS","na_pedido":"2785","cantidad":3,"precio":31.050000000000000710542735760100185871124267578125,"total":93.150000000000005684341886080801486968994140625},{"id_detalle":"1703","id_producto":"948","codigo":"WRA-2640 SY","descripcion":"FILTRO AIRE SECUNDARIO FOTON BJ1166 12TON 6.7L MOTOR CUMMINS ISDE245-30, BJ5166","na_pedido":"2785","cantidad":3,"precio":12,"total":36},{"id_detalle":"1704","id_producto":"1426","codigo":"WRA-3458","descripcion":"FILTRO AIRE PRIMARIO ZX AUTO TERRALORD DIESEL 2.5L, FORD RANGER XLS\/XLT 2.5L","na_pedido":"2788","cantidad":6,"precio":13.4900000000000002131628207280300557613372802734375,"total":80.93999999999999772626324556767940521240234375}]},{"id":"394","id_users":"49","rif":"C-J312069503","nombre_cliente":"PARTES REPUESTOS FILTROS, C.A","num_fact":"17722","num_control":"","fecha_contab":"2026-03-02","fecha_venc":"2026-03-02","valor_moneda":419.987300000000004729372449219226837158203125,"moneda":"USD","iva":87.5520000000000067075234255753457546234130859375,"porcentaje_iva":16,"porcentaje_descuento":0,"descuento":0,"sub_total":547.200000000000045474735088646411895751953125,"total_fact":634.75199999999995270627550780773162841796875,"visto":"Y","nota_credito":null,"DocumentLines":[{"id_detalle":"1299","id_producto":"563","codigo":"W-3612","descripcion":"FILTRO ACEITE CUMMINS. DETROIT DIESEL.","na_pedido":"2780","cantidad":24,"precio":13.5,"total":324},{"id_detalle":"1300","id_producto":"781","codigo":"WPS-7408A","descripcion":"FILTRO COMB\/SEPARADOR CATERPILLAR - JOHN DEERE (ACOPLE RAPIDO)","na_pedido":"2780","cantidad":18,"precio":12.4000000000000003552713678800500929355621337890625,"total":223.19999999999998863131622783839702606201171875}]},{"id":"43","id_users":"49","rif":"C-J312069503","nombre_cliente":"PARTES REPUESTOS FILTROS, C.A","num_fact":"17596","num_control":"32801","fecha_contab":"2026-02-13","fecha_venc":"2026-02-13","valor_moneda":393.22160000000002355591277591884136199951171875,"moneda":"USD","iva":63.73440000000000082991391536779701709747314453125,"porcentaje_iva":16,"porcentaje_descuento":0,"descuento":0,"sub_total":398.33999999999997498889570124447345733642578125,"total_fact":462.07440000000002555680111981928348541259765625,"visto":"N","nota_credito":null,"DocumentLines":[{"id_detalle":"521","id_producto":"615","codigo":"W-977","descripcion":"FILTRO ACEITE BUSES EBRO.FORD CAR","na_pedido":"2692","cantidad":18,"precio":8.300000000000000710542735760100185871124267578125,"total":149.400000000000005684341886080801486968994140625},{"id_detalle":"522","id_producto":"634","codigo":"WP-1121","descripcion":"FILTRO COMBUSTIBLE HERCULES (HERC-40-002510) SECUNDARIO","na_pedido":"2692","cantidad":24,"precio":7.95999999999999996447286321199499070644378662109375,"total":191.039999999999992041921359486877918243408203125},{"id_detalle":"523","id_producto":"979","codigo":"WRF-4023","descripcion":"WEB REFRIGERANTE GOLD AMARILLO 3,78 L","na_pedido":"2692","cantidad":2,"precio":28.949999999999999289457264239899814128875732421875,"total":57.89999999999999857891452847979962825775146484375}]},{"id":"40","id_users":"49","rif":"C-J312069503","nombre_cliente":"PARTES REPUESTOS FILTROS, C.A","num_fact":"17546","num_control":"32751","fecha_contab":"2026-02-09","fecha_venc":"2026-02-09","valor_moneda":382.6317999999999983629095368087291717529296875,"moneda":"USD","iva":116.428799999999995407051756046712398529052734375,"porcentaje_iva":16,"porcentaje_descuento":0,"descuento":0,"sub_total":727.6799999999999499777914024889469146728515625,"total_fact":844.108799999999973806552588939666748046875,"visto":"N","nota_credito":null,"DocumentLines":[{"id_detalle":"490","id_producto":"514","codigo":"WA-10092","descripcion":"FILTRO AIRE FORD FUSION 3.0L 07-09 (FLEXIBLE)","na_pedido":"2692","cantidad":6,"precio":4.4900000000000002131628207280300557613372802734375,"total":26.940000000000001278976924368180334568023681640625},{"id_detalle":"491","id_producto":"1090","codigo":"WA-11952","descripcion":"FILTRO AIRE TOYOTA YARIS 1.5L, ENGINE 2NRFE 19-, RUSH 1.5L 18-","na_pedido":"2692","cantidad":6,"precio":7.5,"total":45},{"id_detalle":"492","id_producto":"1179","codigo":"WA-1578","descripcion":"FILTRO AIRE MAXUS G10 2.0L DI 23-","na_pedido":"2692","cantidad":6,"precio":9,"total":54},{"id_detalle":"493","id_producto":"439","codigo":"WA-1943","descripcion":"FILTRO AIRE  CHEVROLET LUV DMAX 3,5 L  6V  2006-2011","na_pedido":"2692","cantidad":12,"precio":7.5999999999999996447286321199499070644378662109375,"total":91.2000000000000028421709430404007434844970703125},{"id_detalle":"494","id_producto":"441","codigo":"WA-2658","descripcion":"FILTRO AIRE HYUNDAI GETZ   1.3 - 1.6    (28116-1C000)","na_pedido":"2692","cantidad":6,"precio":5.0099999999999997868371792719699442386627197265625,"total":30.059999999999998721023075631819665431976318359375},{"id_detalle":"495","id_producto":"456","codigo":"WA-5056","descripcion":"FILTRO AIRE GRAND MARQUIS - FORD, WIX 46134","na_pedido":"2692","cantidad":12,"precio":7.29000000000000003552713678800500929355621337890625,"total":87.4800000000000039790393202565610408782958984375},{"id_detalle":"496","id_producto":"481","codigo":"WA-7440","descripcion":"FILTRO AIRE JEEP GRAND CHEROKEE - NISSAN PATHFINDER  WIX 46213","na_pedido":"2692","cantidad":6,"precio":7.7400000000000002131628207280300557613372802734375,"total":46.43999999999999772626324556767940521240234375},{"id_detalle":"497","id_producto":"492","codigo":"WA-8069","descripcion":"FILTRO AIRE GRAND VITARA (13780-77E00) WIX 46195","na_pedido":"2692","cantidad":6,"precio":7.410000000000000142108547152020037174224853515625,"total":44.46000000000000085265128291212022304534912109375},{"id_detalle":"498","id_producto":"360","codigo":"WC-1166","descripcion":"FILTRO COMBUSTIBLE CATERPILLAR  CAT-4H-8792","na_pedido":"2692","cantidad":12,"precio":3.45000000000000017763568394002504646778106689453125,"total":41.39999999999999857891452847979962825775146484375},{"id_detalle":"499","id_producto":"9","codigo":"WCA-187","descripcion":"FILTRO AIRE CHEVROLET SILVERADO 8CL, PICK-UP C-6C","na_pedido":"2692","cantidad":6,"precio":4.0999999999999996447286321199499070644378662109375,"total":24.60000000000000142108547152020037174224853515625},{"id_detalle":"500","id_producto":"33","codigo":"WCA-2718","descripcion":"FILTRO AIRE FIAT SPACIO 81\/86. FIORINO 84\/86 UNIVERSAL","na_pedido":"2692","cantidad":24,"precio":3.79999999999999982236431605997495353221893310546875,"total":91.2000000000000028421709430404007434844970703125},{"id_detalle":"501","id_producto":"18","codigo":"WCA-327","descripcion":"FILTRO AIRE MALIBU, MONTECARLOS,CAMARO,CAPRICE","na_pedido":"2692","cantidad":6,"precio":6,"total":36},{"id_detalle":"502","id_producto":"37","codigo":"WCA-3300","descripcion":"FILTRO AIRE MAVERICK, MUSTANG, FAIRMONT 3.3L","na_pedido":"2692","cantidad":6,"precio":4.5,"total":27},{"id_detalle":"503","id_producto":"751","codigo":"WRA-5014","descripcion":"FILTRO AIRE MITSUBISHI CANTER 649 D","na_pedido":"2692","cantidad":6,"precio":13.6500000000000003552713678800500929355621337890625,"total":81.900000000000005684341886080801486968994140625}]},{"id":"39","id_users":"49","rif":"C-J312069503","nombre_cliente":"PARTES REPUESTOS FILTROS, C.A","num_fact":"17545","num_control":"32750","fecha_contab":"2026-02-09","fecha_venc":"2026-02-09","valor_moneda":382.6317999999999983629095368087291717529296875,"moneda":"USD","iva":284.336000000000012732925824820995330810546875,"porcentaje_iva":16,"porcentaje_descuento":0,"descuento":0,"sub_total":1777.09999999999990905052982270717620849609375,"total_fact":2061.43600000000014915713109076023101806640625,"visto":"N","nota_credito":null,"DocumentLines":[{"id_detalle":"471","id_producto":"90","codigo":"WCA-1582","descripcion":"FILTRO AIRE MACK, KENWORTH","na_pedido":"2692","cantidad":2,"precio":35.7000000000000028421709430404007434844970703125,"total":71.400000000000005684341886080801486968994140625},{"id_detalle":"472","id_producto":"100","codigo":"WCA-226","descripcion":"FILTRO AIRE JOHN DEERE 54336, CAT D5, D6, D7, 3208, 140G OEM 4M-9334, 7W-5317","na_pedido":"2692","cantidad":6,"precio":35.9500000000000028421709430404007434844970703125,"total":215.69999999999998863131622783839702606201171875},{"id_detalle":"473","id_producto":"119","codigo":"WCA-2541 SY","descripcion":"FILTRO AIRE SECUNDARIO COMPRESORES SULLAIR","na_pedido":"2692","cantidad":2,"precio":21,"total":42},{"id_detalle":"474","id_producto":"124","codigo":"WCA-256","descripcion":"FILTRO AIRE CLARK, JOHN DEERE","na_pedido":"2692","cantidad":6,"precio":6.9000000000000003552713678800500929355621337890625,"total":41.39999999999999857891452847979962825775146484375},{"id_detalle":"475","id_producto":"127","codigo":"WCA-2590","descripcion":"FILTRO AIRE TRACTOR CATERPILLAR","na_pedido":"2692","cantidad":2,"precio":23.14999999999999857891452847979962825775146484375,"total":46.2999999999999971578290569595992565155029296875},{"id_detalle":"476","id_producto":"941","codigo":"WCA-30079","descripcion":"FILTRO AIRE NEW HOLLAND - LANDINI","na_pedido":"2692","cantidad":1,"precio":49.5499999999999971578290569595992565155029296875,"total":49.5499999999999971578290569595992565155029296875},{"id_detalle":"477","id_producto":"147","codigo":"WCA-330","descripcion":"FILTRO AIRE IVECO 330-30, PEGASO MIDDER","na_pedido":"2692","cantidad":2,"precio":43.89999999999999857891452847979962825775146484375,"total":87.7999999999999971578290569595992565155029296875},{"id_detalle":"478","id_producto":"184","codigo":"WCA-546 SY","descripcion":"FILTRO AIRE SECUNDARIO ALLIS CHALMERS 662608,","na_pedido":"2692","cantidad":2,"precio":16.10000000000000142108547152020037174224853515625,"total":32.2000000000000028421709430404007434844970703125},{"id_detalle":"479","id_producto":"192","codigo":"WCA-598","descripcion":"FILTRO AIRE CATERPILLAR 1P-7716","na_pedido":"2692","cantidad":4,"precio":29.89999999999999857891452847979962825775146484375,"total":119.599999999999994315658113919198513031005859375},{"id_detalle":"480","id_producto":"197","codigo":"WCA-6324","descripcion":"FILTRO AIRE ENCAVA 3100\/2100 - HINO","na_pedido":"2692","cantidad":2,"precio":32.89999999999999857891452847979962825775146484375,"total":65.7999999999999971578290569595992565155029296875},{"id_detalle":"481","id_producto":"201","codigo":"WCA-6512","descripcion":"FILTRO AIRE CAMION MACK SERIE CL 653 57MD42M","na_pedido":"2692","cantidad":4,"precio":60.35000000000000142108547152020037174224853515625,"total":241.400000000000005684341886080801486968994140625},{"id_detalle":"482","id_producto":"212","codigo":"WCA-7244","descripcion":"FILTRO AIRE, ATLAS COPCO, DEUTZ 46430","na_pedido":"2692","cantidad":3,"precio":19.64999999999999857891452847979962825775146484375,"total":58.9500000000000028421709430404007434844970703125},{"id_detalle":"483","id_producto":"213","codigo":"WCA-7244 SY","descripcion":"FILTRO AIRE INTERNATIONAL-IVECO BALDWIN=PA3686, SECUNDARIO","na_pedido":"2692","cantidad":3,"precio":6.9000000000000003552713678800500929355621337890625,"total":20.699999999999999289457264239899814128875732421875},{"id_detalle":"484","id_producto":"216","codigo":"WCA-7454","descripcion":"FILTRO AIRE VOLVO B-58","na_pedido":"2692","cantidad":2,"precio":44.35000000000000142108547152020037174224853515625,"total":88.7000000000000028421709430404007434844970703125},{"id_detalle":"485","id_producto":"254","codigo":"WRA-7476","descripcion":"FILTRO AIRE CATERPILLAR 6I-2509","na_pedido":"2692","cantidad":3,"precio":48.2999999999999971578290569595992565155029296875,"total":144.900000000000005684341886080801486968994140625},{"id_detalle":"486","id_producto":"268","codigo":"WRA-8204","descripcion":"FILTRO AIRE MERCEDES BENZ-PRIM (376 094 82 04)","na_pedido":"2692","cantidad":4,"precio":42.4500000000000028421709430404007434844970703125,"total":169.80000000000001136868377216160297393798828125},{"id_detalle":"487","id_producto":"275","codigo":"WRA-8596","descripcion":"FILTRO AIRE JOHN DEERE. PLANTA ELECTRICA, CATERPILLAR","na_pedido":"2692","cantidad":6,"precio":24.85000000000000142108547152020037174224853515625,"total":149.099999999999994315658113919198513031005859375},{"id_detalle":"488","id_producto":"284","codigo":"WRA-9244","descripcion":"FILTRO AIRE CATERPILLAR 131-8822  - HINO TRUCKS","na_pedido":"2692","cantidad":2,"precio":24.75,"total":49.5},{"id_detalle":"489","id_producto":"290","codigo":"WRA-9869","descripcion":"FILTRO AIRE MACK VISION WIX 42808 MACK 57MD320M","na_pedido":"2692","cantidad":2,"precio":41.14999999999999857891452847979962825775146484375,"total":82.2999999999999971578290569595992565155029296875}]},{"id":"38","id_users":"49","rif":"C-J312069503","nombre_cliente":"PARTES REPUESTOS FILTROS, C.A","num_fact":"17544","num_control":"32749","fecha_contab":"2026-02-09","fecha_venc":"2026-02-09","valor_moneda":382.6317999999999983629095368087291717529296875,"moneda":"USD","iva":262.3808000000000220097717829048633575439453125,"porcentaje_iva":16,"porcentaje_descuento":0,"descuento":0,"sub_total":1639.8800000000001091393642127513885498046875,"total_fact":1902.26080000000001746229827404022216796875,"visto":"Y","nota_credito":null,"DocumentLines":[{"id_detalle":"457","id_producto":"588","codigo":"W-4872","descripcion":"FILTRO ACEITE WH-4A GM- MOTOR ISUZU 4BDIT","na_pedido":"2692","cantidad":6,"precio":6.9000000000000003552713678800500929355621337890625,"total":41.39999999999999857891452847979962825775146484375},{"id_detalle":"458","id_producto":"589","codigo":"W-49","descripcion":"FILTRO ACEITE MACK. KODIAK. CATERPILLAR, VOLVO.","na_pedido":"2692","cantidad":12,"precio":13.160000000000000142108547152020037174224853515625,"total":157.919999999999987494447850622236728668212890625},{"id_detalle":"459","id_producto":"433","codigo":"WC-500-228","descripcion":"FILTRO COMBUSTIBLE CAMION PEGASO,ENASA 500-228 ORIGINAL 550","na_pedido":"2692","cantidad":60,"precio":2.75,"total":165},{"id_detalle":"460","id_producto":"1184","codigo":"WC-634","descripcion":"FILTRO COMBUSTIBLE PRIMARIO SINOTRUK BOLDEN S6, S7, S9","na_pedido":"2692","cantidad":6,"precio":11,"total":66},{"id_detalle":"461","id_producto":"639","codigo":"WP-1146","descripcion":"FILTRO COMBUSTIBLE DETROIT DIESEL (ACT815)PRIM. FREIGHTLINER","na_pedido":"2692","cantidad":18,"precio":8.230000000000000426325641456060111522674560546875,"total":148.1399999999999863575794734060764312744140625},{"id_detalle":"462","id_producto":"640","codigo":"WP-1147","descripcion":"FILTRO COMBUSTIBLE DETROIT DIESEL SECUND.FREIGHTLINER","na_pedido":"2692","cantidad":18,"precio":7.54999999999999982236431605997495353221893310546875,"total":135.900000000000005684341886080801486968994140625},{"id_detalle":"463","id_producto":"661","codigo":"WP-4637","descripcion":"FILTRO ACEITE HIDR\u00c1ULICO FORD F-8000, TRACTOR 6600","na_pedido":"2692","cantidad":24,"precio":8.199999999999999289457264239899814128875732421875,"total":196.80000000000001136868377216160297393798828125},{"id_detalle":"464","id_producto":"998","codigo":"WPS-3030","descripcion":"FILTRO COMBUSTIBLE SECUNDARIO JAC T6, T8 DIESEL 16-","na_pedido":"2692","cantidad":12,"precio":10.5,"total":126},{"id_detalle":"465","id_producto":"1163","codigo":"WPS-36209","descripcion":"FILTRO COMB\/SEPARADOR FOTON AUMARK S Y C, G7","na_pedido":"2692","cantidad":6,"precio":14.800000000000000710542735760100185871124267578125,"total":88.7999999999999971578290569595992565155029296875},{"id_detalle":"466","id_producto":"970","codigo":"WPS-3712","descripcion":"FILTRO COMB\/SEPARADOR CUMMINS, CON DRENAJE M8 X 1,5H (ANTES WP-1103P)","na_pedido":"2692","cantidad":12,"precio":11.03999999999999914734871708787977695465087890625,"total":132.479999999999989768184605054557323455810546875},{"id_detalle":"467","id_producto":"1059","codigo":"WPS-421","descripcion":"FILTRO COMB\/SEPARADOR HOWO T5G MC07.24-30 (UN DRENAJE)","na_pedido":"2692","cantidad":6,"precio":16.469999999999998863131622783839702606201171875,"total":98.81999999999999317878973670303821563720703125},{"id_detalle":"468","id_producto":"997","codigo":"WPS-5151","descripcion":"FILTRO COMB\/SEPARADOR CAMIONES HOWO, SANY MOTOR YUCHAI YC4D140-33; 4,21LT","na_pedido":"2692","cantidad":11,"precio":9.4000000000000003552713678800500929355621337890625,"total":103.400000000000005684341886080801486968994140625},{"id_detalle":"469","id_producto":"689","codigo":"WPS-7177","descripcion":"FILTRO COMB\/SEPARADOR FORD CARGO 1721- MOTOR CUMMINS 6CTTA, USAR CON VASO, ROSCA 1 X14H,","na_pedido":"2692","cantidad":6,"precio":11.8699999999999992184029906638897955417633056640625,"total":71.219999999999998863131622783839702606201171875},{"id_detalle":"470","id_producto":"1196","codigo":"WPS-P31F0","descripcion":"FILTRO COMBUSTIBLE JAC T9 DIESEL 2,0L 23-","na_pedido":"2692","cantidad":12,"precio":9,"total":108}]}]